{
  "lastUpdated": "2026-03-18T11:40:01.915Z",
  "version": 97,
  "phi": 1.618033988749895,
  "resourcePatterns": [
    {
      "type": "RESOURCE_STABLE",
      "confidence": 1,
      "severity": "LOW",
      "firstSeen": "2026-03-18T03:35:01.395Z",
      "lastSeen": "2026-03-18T11:40:01.915Z",
      "occurrences": 97
    }
  ],
  "gitVelocity": "HIGH",
  "commitCount24h": 289,
  "topTopics": [
    {
      "word": "file(s)",
      "count": 229
    },
    {
      "word": "hcfp-auto",
      "count": 186
    },
    {
      "word": "changed",
      "count": 186
    },
    {
      "word": "auto-commit.log",
      "count": 150
    },
    {
      "word": "pattern_store.json",
      "count": 140
    },
    {
      "word": "resource-events.jsonl",
      "count": 69
    },
    {
      "word": "chore(auto)",
      "count": 43
    },
    {
      "word": "auto-commit",
      "count": 43
    },
    {
      "word": "feat",
      "count": 36
    },
    {
      "word": "stories.json",
      "count": 16
    }
  ]
}